permpy/InsertionEncoding/__init__.py
permpy/InsertionEncoding/configuration.py
permpy/InsertionEncoding/insertionscheme.py
permpy/PegPermutations/__init__.py
permpy/PegPermutations/pegpermset.py
permpy/PegPermutations/pegpermutation.py
permpy/PegPermutations/vector.py
permpy/PegPermutations/vectorset.py
permpy/RestrictedContainer/__init__.py
permpy/RestrictedContainer/restricted_container.py
permpy/__init__.py
permpy/avclass.py
permpy/deprecated/__init__.py
permpy/deprecated/permclassdeprecated.py
permpy/deprecated/permdeprecated.py
permpy/deprecated/permsetdeprecated.py
permpy/geometricgridclass.py
permpy/permclass.py
permpy/permmisc.py
permpy/permset.py
permpy/permstats.py
permpy/permutation.py
permpy/propertyclass.py
permpy/staircase.py
permpy/test_geometricgridclass.py
permpy/utils.py
permpy-0.2.12.dist-info/LICENSE.txt
permpy-0.2.12.dist-info/METADATA
permpy-0.2.12.dist-info/WHEEL
permpy-0.2.12.dist-info/RECORD
